fred_framework/__init__.py
fred_framework/create_module.py
fred_framework/install_hook.py
fred_framework/代码规范.md
fred_framework/common/AliyunSms.py
fred_framework/common/Blueprints.py
fred_framework/common/Email.py
fred_framework/common/Extensions.py
fred_framework/common/HandleExcetion.py
fred_framework/common/ImageVerification.py
fred_framework/common/IoTDBClient.py
fred_framework/common/PageSchema.py
fred_framework/common/Response.py
fred_framework/common/Route.py
fred_framework/common/SchedulerLog.py
fred_framework/common/Sqlacodegen.py
fred_framework/common/Swagger.py
fred_framework/common/SystemLog.py
fred_framework/common/Utils.py
fred_framework/common/WechatLogin.py
fred_framework/common/__init__.py
fred_framework/config/Config.py
fred_framework/config/Logger.py
fred_framework/config/__init__.py
fred_framework/demo/README.md
fred_framework/demo/__init__.py
fred_framework/demo/common/__init__.py
fred_framework/demo/constant/RedisKey.py
fred_framework/demo/controller/AdminAuthController.py
fred_framework/demo/controller/AdminController.py
fred_framework/demo/controller/ButtonManageController.py
fred_framework/demo/controller/FileController.py
fred_framework/demo/controller/OrganizationController.py
fred_framework/demo/controller/RoleController.py
fred_framework/demo/controller/SystemController.py
fred_framework/demo/controller/SystemLogController.py
fred_framework/demo/controller/TableController.py
fred_framework/demo/controller/__init__.py
fred_framework/demo/frontend/LICENSE
fred_framework/demo/frontend/commitlint.config.cjs
fred_framework/demo/frontend/demo_editorconfig
fred_framework/demo/frontend/demo_env
fred_framework/demo/frontend/demo_env.development
fred_framework/demo/frontend/demo_env.production
fred_framework/demo/frontend/demo_eslintignore
fred_framework/demo/frontend/demo_eslintrc.cjs
fred_framework/demo/frontend/demo_gitignore
fred_framework/demo/frontend/demo_prettierignore
fred_framework/demo/frontend/demo_prettierrc.cjs
fred_framework-1.2.3.dist-info/licenses/LICENSE
fred_framework-1.2.3.dist-info/METADATA
fred_framework-1.2.3.dist-info/WHEEL
fred_framework-1.2.3.dist-info/entry_points.txt
fred_framework-1.2.3.dist-info/top_level.txt
fred_framework-1.2.3.dist-info/RECORD
